pytoon/__init__.py
pytoon/decoder.py
pytoon/encoder.py
pytoon/errors.py
pytoon/scalars.py
pytoon_lite-0.1.0.dist-info/METADATA
pytoon_lite-0.1.0.dist-info/WHEEL
pytoon_lite-0.1.0.dist-info/top_level.txt
pytoon_lite-0.1.0.dist-info/RECORD
