Metadata-Version: 2.4
Name: pytoon-lite
Version: 0.1.0
Summary: Lightweight Python encoder/decoder for TOON (Token-Oriented Object Notation)
Author-email: Evgenii Saurov <saurov.ev@gmail.com>
License: MIT
Project-URL: Homepage, https://example.com/pytoon
Project-URL: Source Code, https://example.com/pytoon
Keywords: TOON,serialization,LLM,json
Classifier: Programming Language :: Python :: 3
Classifier: Programming Language :: Python :: 3 :: Only
Classifier: License :: OSI Approved :: MIT License
Classifier: Intended Audience :: Developers
Classifier: Topic :: Software Development :: Libraries :: Python Modules
Requires-Python: >=3.9
Provides-Extra: dev
Requires-Dist: pytest; extra == "dev"
Requires-Dist: ruff; extra == "dev"
Requires-Dist: mypy; extra == "dev"
